{
  "TheUltimateTON": "The ultimate TON wallet",
  "DesignedSecure": "Designed to keep your digital assets safe and secure.",
  "ComingSoon": "Coming soon",
  "Features": "TON SAFE Features",
  "MultipleWallets": "Multiple wallets",
  "MultipleWallets_Text": "Multiple wallets architecture to allow maximum flexibility.",
  "Staking": "Staking",
  "Staking_Text": "Simple staking to earn passive income and support the security and stability of TON network.",
  "NFT": "NFT",
  "NFT_Text": "Securely store, share and view your NFTs.",
  "Swap": "Swap",
  "Swap_Text": "Exchange tokens without leaving the app.",
  "MultisigVault": "Multisig vault",
  "MultisigVault_Text": "Increased security: multiple keys are required to authorize a transaction.",
  "Browser": "Browser",
  "Browser_Text": "Browser for TON sites and DeFi ecosystem.",
  "GetItNow": "Get it now on  AppStore or GooglePlay",
  "Copyrights": "© TON Safe app",
  "FollowUs": "Follow us"
}
